apng/__init__.py
apng-0.3.4.dist-info/LICENSE
apng-0.3.4.dist-info/METADATA
apng-0.3.4.dist-info/WHEEL
apng-0.3.4.dist-info/top_level.txt
apng-0.3.4.dist-info/zip-safe
apng-0.3.4.dist-info/RECORD
