Metadata-Version: 1.1
Name: apng
Version: 0.3.4
Summary: A Python module to deal with APNG file.
Home-page: https://github.com/eight04/pyAPNG
Author: eight
Author-email: eight04@gmail.com
License: MIT
Keywords: png,apng,image,convert
Platform: UNKNOWN
Classifier: Development Status :: 5 - Production/Stable
Classifier: Intended Audience :: Developers
Classifier: License :: OSI Approved :: MIT License
Classifier: Natural Language :: Chinese (Traditional)
Classifier: Programming Language :: Python :: 2.7
Classifier: Programming Language :: Python :: 3.5
Classifier: Programming Language :: Python :: 3.6
Classifier: Topic :: Multimedia :: Graphics :: Graphics Conversion
